[{"Team":"Ace Classifiers - Amartya Ponugoti","Score":83.0},{"Team":"Piro - Ayush Jha","Score":76.0},{"Team":"Piro - Ayush Jha (1)","Score":74.5},{"Team":"SignalShifters - R0NIT","Score":74.5},{"Team":"ice cube - Vedant Neekhra","Score":71.5},{"Team":"enCODERz - nithin b","Score":70.0},{"Team":"LeafyGreen - S Kiran","Score":70.0},{"Team":"LeafyGreen(3) - S Kiran","Score":70.0},{"Team":"Signalsprint Research - Shohom De","Score":69.0},{"Team":"Signalsprint Research - Shohom De (1)","Score":69.0},{"Team":"Aviators - Rigved Koli","Score":68.5},{"Team":"Signalsprint Research (3) - Shohom De","Score":68.5},{"Team":"Signalsprint Research  - Shohom De","Score":68.0},{"Team":"Signals_and_Circuits - Rajkumar Ahirwar","Score":65.0},{"Team":"Timepass - Kinshuk Joshi","Score":60.0},{"Team":"Convolution - Pallav Rastogi","Score":33.0},{"Team":"sap - Shashwat Parikh","Score":28.0},{"Team":"Convolution - Pallav Rastogi (1)","Score":28.0},{"Team":"BlackBox - Shivansh","Score":0.0}]